aws_xray_sdk-stubs/METADATA.toml
aws_xray_sdk-stubs/__init__.pyi
aws_xray_sdk-stubs/py.typed
aws_xray_sdk-stubs/sdk_config.pyi
aws_xray_sdk-stubs/version.pyi
aws_xray_sdk-stubs/core/__init__.pyi
aws_xray_sdk-stubs/core/async_context.pyi
aws_xray_sdk-stubs/core/async_recorder.pyi
aws_xray_sdk-stubs/core/context.pyi
aws_xray_sdk-stubs/core/daemon_config.pyi
aws_xray_sdk-stubs/core/lambda_launcher.pyi
aws_xray_sdk-stubs/core/patcher.pyi
aws_xray_sdk-stubs/core/recorder.pyi
aws_xray_sdk-stubs/core/emitters/__init__.pyi
aws_xray_sdk-stubs/core/emitters/udp_emitter.pyi
aws_xray_sdk-stubs/core/exceptions/__init__.pyi
aws_xray_sdk-stubs/core/exceptions/exceptions.pyi
aws_xray_sdk-stubs/core/models/__init__.pyi
aws_xray_sdk-stubs/core/models/default_dynamic_naming.pyi
aws_xray_sdk-stubs/core/models/dummy_entities.pyi
aws_xray_sdk-stubs/core/models/entity.pyi
aws_xray_sdk-stubs/core/models/facade_segment.pyi
aws_xray_sdk-stubs/core/models/http.pyi
aws_xray_sdk-stubs/core/models/noop_traceid.pyi
aws_xray_sdk-stubs/core/models/segment.pyi
aws_xray_sdk-stubs/core/models/subsegment.pyi
aws_xray_sdk-stubs/core/models/throwable.pyi
aws_xray_sdk-stubs/core/models/trace_header.pyi
aws_xray_sdk-stubs/core/models/traceid.pyi
aws_xray_sdk-stubs/core/plugins/__init__.pyi
aws_xray_sdk-stubs/core/plugins/ec2_plugin.pyi
aws_xray_sdk-stubs/core/plugins/ecs_plugin.pyi
aws_xray_sdk-stubs/core/plugins/elasticbeanstalk_plugin.pyi
aws_xray_sdk-stubs/core/plugins/utils.pyi
aws_xray_sdk-stubs/core/sampling/__init__.pyi
aws_xray_sdk-stubs/core/sampling/connector.pyi
aws_xray_sdk-stubs/core/sampling/reservoir.pyi
aws_xray_sdk-stubs/core/sampling/rule_cache.pyi
aws_xray_sdk-stubs/core/sampling/rule_poller.pyi
aws_xray_sdk-stubs/core/sampling/sampler.pyi
aws_xray_sdk-stubs/core/sampling/sampling_rule.pyi
aws_xray_sdk-stubs/core/sampling/target_poller.pyi
aws_xray_sdk-stubs/core/sampling/local/__init__.pyi
aws_xray_sdk-stubs/core/sampling/local/reservoir.pyi
types_aws_xray_sdk-2.15.0.20251111.dist-info/licenses/LICENSE
types_aws_xray_sdk-2.15.0.20251111.dist-info/METADATA
types_aws_xray_sdk-2.15.0.20251111.dist-info/WHEEL
types_aws_xray_sdk-2.15.0.20251111.dist-info/top_level.txt
types_aws_xray_sdk-2.15.0.20251111.dist-info/RECORD
